<?xml version="1.0" encoding="UTF-8" standalone="yes"?>
<test numberOfQuestions="2" testName="231">
    <questions>
        <question questionContent="213" number="1">
            <answers>
                <answer symbol="65" content="sad" correct="false"/>
                <answer symbol="66" content="sad" correct="false"/>
                <answer symbol="67" content="sad" correct="true"/>
                <answer symbol="68" content="sad" correct="false"/>
            </answers>
            <correctAnswer symbol="67" content="sad" correct="true"/>
        </question>
        <question questionContent="asda" number="2">
            <answers>
                <answer symbol="65" content="asdas" correct="false"/>
                <answer symbol="66" content="asdas" correct="false"/>
                <answer symbol="67" content="asdas" correct="true"/>
                <answer symbol="68" content="asdas" correct="false"/>
            </answers>
            <correctAnswer symbol="67" content="asdas" correct="true"/>
        </question>
    </questions>
</test>
